remote_play_3ds/__init__.py
remote_play_3ds/__main__.py
remote_play_3ds/static/js/index.js
remote_play_3ds/templates/index.html
remote_play_3ds-0.1.0.dist-info/LICENSE
remote_play_3ds-0.1.0.dist-info/METADATA
remote_play_3ds-0.1.0.dist-info/WHEEL
remote_play_3ds-0.1.0.dist-info/RECORD
