Metadata-Version: 2.1
Name: remote-play-3ds
Version: 0.1.0
Summary: Remote play your modded 3DS.
Home-page: https://github.com/U-1F992/remote-play-3ds
Author: Koutaro Mukai
Author-email: mukai.k1011k@outlook.jp
Requires-Python: >=3.12,<4.0
Classifier: Programming Language :: Python :: 3
Classifier: Programming Language :: Python :: 3.12
Requires-Dist: flask (>=3.0.0,<4.0.0)
Requires-Dist: opencv-python-headless (>=4.9.0.80,<5.0.0.0)
Requires-Dist: qingpi-python (>=0.1.10,<0.2.0)
Project-URL: Repository, https://github.com/U-1F992/remote-play-3ds
